{
  "variants": {
    "inventory": {
      "model": "moarboats:block/energy_discharger"
    },
    "facing=down": {
      "model": "moarboats:block/energy_discharger",
      "x": 180
    },
    "facing=up": {
      "model": "moarboats:block/energy_discharger"
    },
    "facing=north": {
      "model": "moarboats:block/energy_discharger",
      "x": 90
    },
    "facing=south": {
      "model": "moarboats:block/energy_discharger",
      "x": 270
    },
    "facing=west": {
      "model": "moarboats:block/energy_discharger",
      "x": 90,
      "y": 270
    },
    "facing=east": {
      "model": "moarboats:block/energy_discharger",
      "x": 90,
      "y": 90
    }
  }
}